robust_gymnasium/__init__.py
robust_gymnasium/core.py
robust_gymnasium/error.py
robust_gymnasium/functional.py
robust_gymnasium/logger.py
robust_gymnasium/py.typed
robust_gymnasium/configs/__init__.py
robust_gymnasium/configs/robust_setting.py
robust_gymnasium/envs/__init__.py
robust_gymnasium/envs/functional_jax_env.py
robust_gymnasium/envs/gymnasium_robotics_core.py
robust_gymnasium/envs/registration.py
robust_gymnasium/envs/robot_env.py
robust_gymnasium/envs/classic_control/__init__.py
robust_gymnasium/envs/classic_control/acrobot.py
robust_gymnasium/envs/classic_control/cartpole.py
robust_gymnasium/envs/classic_control/continuous_mountain_car.py
robust_gymnasium/envs/classic_control/mountain_car.py
robust_gymnasium/envs/classic_control/pendulum.py
robust_gymnasium/envs/classic_control/utils.py
robust_gymnasium/envs/classic_control/assets/clockwise.png
robust_gymnasium/envs/llm_guide_robust/gpt_collect.py
robust_gymnasium/envs/llm_guide_robust/llm.py
robust_gymnasium/envs/mujoco/__init__.py
robust_gymnasium/envs/mujoco/ant.py
robust_gymnasium/envs/mujoco/ant_v3.py
robust_gymnasium/envs/mujoco/ant_v4.py
robust_gymnasium/envs/mujoco/ant_v5.py
robust_gymnasium/envs/mujoco/half_cheetah.py
robust_gymnasium/envs/mujoco/half_cheetah_v3.py
robust_gymnasium/envs/mujoco/half_cheetah_v4.py
robust_gymnasium/envs/mujoco/half_cheetah_v5.py
robust_gymnasium/envs/mujoco/hopper.py
robust_gymnasium/envs/mujoco/hopper_v3.py
robust_gymnasium/envs/mujoco/hopper_v4.py
robust_gymnasium/envs/mujoco/hopper_v5.py
robust_gymnasium/envs/mujoco/humanoid.py
robust_gymnasium/envs/mujoco/humanoid_v3.py
robust_gymnasium/envs/mujoco/humanoid_v4.py
robust_gymnasium/envs/mujoco/humanoid_v5.py
robust_gymnasium/envs/mujoco/humanoidstandup.py
robust_gymnasium/envs/mujoco/humanoidstandup_v4.py
robust_gymnasium/envs/mujoco/humanoidstandup_v5.py
robust_gymnasium/envs/mujoco/inverted_double_pendulum.py
robust_gymnasium/envs/mujoco/inverted_double_pendulum_v4.py
robust_gymnasium-0.1.3.dist-info/licenses/LICENSE
robust_gymnasium-0.1.3.dist-info/METADATA
robust_gymnasium-0.1.3.dist-info/WHEEL
robust_gymnasium-0.1.3.dist-info/top_level.txt
robust_gymnasium-0.1.3.dist-info/RECORD
