Metadata-Version: 2.4
Name: robust_gymnasium
Version: 0.1.3
Summary: A standard API for robust reinforcement learning and a diverse set of reference environments (formerly Gym).
Home-page: https://github.com/SafeRL-Lab/Robust-Gymnasium
Author: Safe RL Lab
Author-email: Safe RL Lab <contact@saferl.org>
License: MIT License
Project-URL: Homepage, https://github.com/SafeRL-Lab
Project-URL: Repository, https://github.com/SafeRL-Lab/Robust-Gymnasium
Project-URL: Documentation, https://github.com/SafeRL-Lab/Robust-Gymnasium
Project-URL: Bug Report, https://github.com/SafeRL-Lab/Robust-Gymnasium/issues
Keywords: Reinforcement Learning,game,RL,AI,robust_gymnasium
Classifier: Development Status :: 4 - Beta
Classifier: License :: OSI Approved :: MIT License
Classifier: Programming Language :: Python :: 3
Classifier: Programming Language :: Python :: 3.8
Classifier: Programming Language :: Python :: 3.9
Classifier: Programming Language :: Python :: 3.10
Classifier: Programming Language :: Python :: 3.11
Classifier: Programming Language :: Python :: 3.12
Classifier: Intended Audience :: Science/Research
Classifier: Topic :: Scientific/Engineering :: Artificial Intelligence
Requires-Python: >=3.8
License-File: LICENSE
Requires-Dist: numpy>=1.21.0
Requires-Dist: cloudpickle>=1.2.0
Requires-Dist: importlib-metadata>=4.8.0; python_version < "3.10"
Requires-Dist: typing-extensions>=4.3.0
Requires-Dist: farama-notifications>=0.0.1
Requires-Dist: swig==4.2.1
Requires-Dist: pygame==2.1.3
Requires-Dist: ufal.pybox2d>=2.3.10.3
Requires-Dist: gymnasium[mujoco]
Requires-Dist: numpy>=1.13.3
Requires-Dist: numba>=0.49.1
Requires-Dist: scipy>=1.2.3
Requires-Dist: mujoco>=2.3.0
Requires-Dist: Pillow
Requires-Dist: opencv-python
Requires-Dist: pynput
Requires-Dist: termcolor
Requires-Dist: pybullet-svl>=3.1.6.4
Requires-Dist: gymnasium
Requires-Dist: hidapi
Requires-Dist: h5py
Requires-Dist: open3d
Requires-Dist: pettingzoo>=1.24.3
Requires-Dist: dm_control>=1.0.20
Requires-Dist: gymnasium>=0.29.1
Requires-Dist: jax>=0.4.30
Requires-Dist: openai
Requires-Dist: sphinx
Requires-Dist: sphinx-book-theme
Provides-Extra: atari
Requires-Dist: ale_py>=0.9; extra == "atari"
Provides-Extra: box2d
Requires-Dist: box2d-py==2.3.5; extra == "box2d"
Requires-Dist: pygame>=2.1.3; extra == "box2d"
Requires-Dist: swig==4.*; extra == "box2d"
Provides-Extra: classic-control
Requires-Dist: pygame>=2.1.3; extra == "classic-control"
Provides-Extra: classic-control
Requires-Dist: pygame>=2.1.3; extra == "classic-control"
Provides-Extra: mujoco-py
Requires-Dist: mujoco-py<2.2,>=2.1; extra == "mujoco-py"
Requires-Dist: cython<3; extra == "mujoco-py"
Provides-Extra: mujoco-py
Requires-Dist: mujoco-py<2.2,>=2.1; extra == "mujoco-py"
Requires-Dist: cython<3; extra == "mujoco-py"
Provides-Extra: mujoco
Requires-Dist: mujoco>=2.1.5; extra == "mujoco"
Requires-Dist: imageio>=2.14.1; extra == "mujoco"
Provides-Extra: toy-text
Requires-Dist: pygame>=2.1.3; extra == "toy-text"
Provides-Extra: toy-text
Requires-Dist: pygame>=2.1.3; extra == "toy-text"
Provides-Extra: jax
Requires-Dist: jax>=0.4.0; extra == "jax"
Requires-Dist: jaxlib>=0.4.0; extra == "jax"
Requires-Dist: flax>=0.5.0; extra == "jax"
Provides-Extra: torch
Requires-Dist: torch>=1.0.0; extra == "torch"
Provides-Extra: other
Requires-Dist: moviepy>=1.0.0; extra == "other"
Requires-Dist: matplotlib>=3.0; extra == "other"
Requires-Dist: opencv-python>=3.0; extra == "other"
Provides-Extra: all
Requires-Dist: numpy>=1.13.3; extra == "all"
Requires-Dist: numba>=0.49.1; extra == "all"
Requires-Dist: scipy>=1.2.3; extra == "all"
Requires-Dist: mujoco>=2.3.0; extra == "all"
Requires-Dist: Pillow; extra == "all"
Requires-Dist: opencv-python; extra == "all"
Requires-Dist: pynput; extra == "all"
Requires-Dist: termcolor; extra == "all"
Requires-Dist: ufal.pybox2d>=2.3.10.3; extra == "all"
Requires-Dist: gymnasium[mujoco]; extra == "all"
Requires-Dist: gymnasium[box2d]; extra == "all"
Requires-Dist: gymnasium>=0.29.1; extra == "all"
Requires-Dist: dm_control>=1.0.20; extra == "all"
Requires-Dist: jax>=0.4.30; extra == "all"
Requires-Dist: pettingzoo>=1.24.3; extra == "all"
Requires-Dist: pybullet-svl>=3.1.6.4; extra == "all"
Requires-Dist: h5py; extra == "all"
Requires-Dist: open3d; extra == "all"
Requires-Dist: openai; extra == "all"
Requires-Dist: cloudpickle>=1.2.0; extra == "all"
Requires-Dist: typing-extensions>=4.3.0; extra == "all"
Requires-Dist: farama-notifications>=0.0.1; extra == "all"
Requires-Dist: hidapi; extra == "all"
Requires-Dist: ale_py>=0.9; extra == "all"
Requires-Dist: box2d-py==2.3.5; extra == "all"
Requires-Dist: pygame>=2.1.3; extra == "all"
Requires-Dist: swig==4.*; extra == "all"
Requires-Dist: mujoco-py<2.2,>=2.1; extra == "all"
Requires-Dist: cython<3; extra == "all"
Requires-Dist: mujoco>=2.1.5; extra == "all"
Requires-Dist: imageio>=2.14.1; extra == "all"
Requires-Dist: jaxlib>=0.4.0; extra == "all"
Requires-Dist: flax>=0.5.0; extra == "all"
Requires-Dist: torch>=1.0.0; extra == "all"
Requires-Dist: matplotlib>=3.0; extra == "all"
Requires-Dist: moviepy>=1.0.0; extra == "all"
Provides-Extra: testing
Requires-Dist: pytest==7.1.3; extra == "testing"
Requires-Dist: scipy>=1.7.3; extra == "testing"
Requires-Dist: dill>=0.3.7; extra == "testing"
Dynamic: author
Dynamic: home-page
Dynamic: license-file
Dynamic: requires-python
